lftools_uv/__init__.py
lftools_uv/cli_app.py
lftools_uv/config.py
lftools_uv/conftest.py
lftools_uv/deploy.py
lftools_uv/github_helper.py
lftools_uv/helpers.py
lftools_uv/ldap_cli.py
lftools_uv/lfidapi.py
lftools_uv/license.py
lftools_uv/oauth2_helper.py
lftools_uv/schema.py
lftools_uv/api/__init__.py
lftools_uv/api/client.py
lftools_uv/api/exceptions.py
lftools_uv/api/endpoints/__init__.py
lftools_uv/api/endpoints/gerrit.py
lftools_uv/api/endpoints/nexus2.py
lftools_uv/api/endpoints/nexus3.py
lftools_uv/api/endpoints/readthedocs.py
lftools_uv/cli/__init__.py
lftools_uv/cli/config.py
lftools_uv/cli/dco.py
lftools_uv/cli/deploy.py
lftools_uv/cli/errors.py
lftools_uv/cli/gerrit.py
lftools_uv/cli/github_cli.py
lftools_uv/cli/infofile.py
lftools_uv/cli/ldap_cli.py
lftools_uv/cli/lfidapi.py
lftools_uv/cli/license.py
lftools_uv/cli/nexus.py
lftools_uv/cli/no_cmd.py
lftools_uv/cli/rtd.py
lftools_uv/cli/schema.py
lftools_uv/cli/sign.py
lftools_uv/cli/state.py
lftools_uv/cli/utils.py
lftools_uv/cli/version.py
lftools_uv/cli/jenkins/__init__.py
lftools_uv/cli/jenkins/builds.py
lftools_uv/cli/jenkins/jobs.py
lftools_uv/cli/jenkins/nodes.py
lftools_uv/cli/jenkins/plugins.py
lftools_uv/cli/jenkins/token.py
lftools_uv/cli/nexus2/__init__.py
lftools_uv/cli/nexus2/privilege.py
lftools_uv/cli/nexus2/repository.py
lftools_uv/cli/nexus2/role.py
lftools_uv/cli/nexus2/user.py
lftools_uv/cli/nexus3/__init__.py
lftools_uv/cli/nexus3/asset.py
lftools_uv/cli/nexus3/privilege.py
lftools_uv/cli/nexus3/repository.py
lftools_uv/cli/nexus3/role.py
lftools_uv/cli/nexus3/script.py
lftools_uv/cli/nexus3/tag.py
lftools_uv/cli/nexus3/task.py
lftools_uv/cli/nexus3/user.py
lftools_uv/git/__init__.py
lftools_uv/git/gerrit.py
lftools_uv/git/templates/config-params.yaml
lftools_uv/git/templates/gitreview
lftools_uv/git/templates/project.yaml
lftools_uv/git/templates/serverCredentialMappings.yaml
lftools_uv/jenkins/__init__.py
lftools_uv/jenkins/token.py
lftools_uv/nexus/__init__.py
lftools_uv-0.1.5.dist-info/METADATA
lftools_uv-0.1.5.dist-info/WHEEL
lftools_uv-0.1.5.dist-info/entry_points.txt
lftools_uv-0.1.5.dist-info/RECORD
