Metadata-Version: 2.4
Name: lftools-uv
Version: 0.1.5
Summary: Linux Foundation Release Engineering Tools
Project-URL: Homepage, https://docs.releng.linuxfoundation.org/projects/lftools-uv
Project-URL: Bug Tracker, https://github.com/lfit/lftools-uv/issues
Project-URL: Documentation, https://docs.releng.linuxfoundation.org/projects/lftools-uv
Project-URL: GitHub Pages, https://modeseven-lfit.github.io/lftools-uv/
Project-URL: Source Code, https://github.com/lfit/lftools-uv
Project-URL: Repository, https://github.com/lfit/lftools-uv
Project-URL: Changelog, https://github.com/lfit/lftools-uv/releases
Author-email: LF Release Engineering <releng@linuxfoundation.org>
Maintainer-email: LF Release Engineering <releng@linuxfoundation.org>
License: EPL-1.0 OR Apache-2.0
Classifier: Intended Audience :: Developers
Classifier: Intended Audience :: Information Technology
Classifier: License :: OSI Approved :: Eclipse Public License 1.0 (EPL-1.0)
Classifier: Operating System :: POSIX :: Linux
Classifier: Programming Language :: Python
Classifier: Programming Language :: Python :: 3.11
Classifier: Programming Language :: Python :: 3.12
Classifier: Programming Language :: Python :: 3.13
Requires-Python: >=3.11
Requires-Dist: attrs
Requires-Dist: beautifulsoup4
Requires-Dist: boto3
Requires-Dist: certifi
Requires-Dist: cfgv
Requires-Dist: click
Requires-Dist: defusedxml
Requires-Dist: deprecated
Requires-Dist: dnspython
Requires-Dist: docker
Requires-Dist: email-validator
Requires-Dist: filelock
Requires-Dist: gitpython
Requires-Dist: google-auth
Requires-Dist: google-auth-oauthlib
Requires-Dist: identify
Requires-Dist: idna
Requires-Dist: jinja2
Requires-Dist: jsonschema
Requires-Dist: lxml
Requires-Dist: nodeenv
Requires-Dist: openstacksdk<5.0.0,>=4.0.0
Requires-Dist: pbr
Requires-Dist: platformdirs
Requires-Dist: pygerrit2
Requires-Dist: pygithub
Requires-Dist: pyjwt
Requires-Dist: python-jenkins
Requires-Dist: pyyaml
Requires-Dist: requests>=2.32.0
Requires-Dist: ruamel-yaml
Requires-Dist: ruamel-yaml-clib
Requires-Dist: soupsieve
Requires-Dist: tabulate
Requires-Dist: tqdm
Requires-Dist: typer
Requires-Dist: urllib3<3.0.0,>=2.2.3
Requires-Dist: websocket-client
Requires-Dist: wrapt
Provides-Extra: all
Requires-Dist: bandit; extra == 'all'
Requires-Dist: boto3-stubs; extra == 'all'
Requires-Dist: mypy; extra == 'all'
Requires-Dist: osc-lib~=2.2.0; extra == 'all'
Requires-Dist: pre-commit; extra == 'all'
Requires-Dist: pytest-click>=1.1.0; extra == 'all'
Requires-Dist: pytest-cov>=5.0.0; extra == 'all'
Requires-Dist: pytest-datafiles>=3.0.0; extra == 'all'
Requires-Dist: pytest-mock>=3.14.0; extra == 'all'
Requires-Dist: pytest-responses>=0.5.1; extra == 'all'
Requires-Dist: pytest>=8.3.0; extra == 'all'
Requires-Dist: python-ldap<4.0,>=3.4; extra == 'all'
Requires-Dist: ruff; extra == 'all'
Requires-Dist: safety; extra == 'all'
Requires-Dist: tox; extra == 'all'
Requires-Dist: types-deprecated; extra == 'all'
Requires-Dist: types-jsonschema; extra == 'all'
Requires-Dist: types-pyyaml; extra == 'all'
Requires-Dist: types-requests; extra == 'all'
Requires-Dist: types-tabulate; extra == 'all'
Requires-Dist: types-tqdm; extra == 'all'
Provides-Extra: dev
Requires-Dist: bandit; extra == 'dev'
Requires-Dist: boto3-stubs; extra == 'dev'
Requires-Dist: mypy; extra == 'dev'
Requires-Dist: pre-commit; extra == 'dev'
Requires-Dist: ruff; extra == 'dev'
Requires-Dist: safety; extra == 'dev'
Requires-Dist: tox; extra == 'dev'
Requires-Dist: types-deprecated; extra == 'dev'
Requires-Dist: types-jsonschema; extra == 'dev'
Requires-Dist: types-pyyaml; extra == 'dev'
Requires-Dist: types-requests; extra == 'dev'
Requires-Dist: types-tabulate; extra == 'dev'
Requires-Dist: types-tqdm; extra == 'dev'
Provides-Extra: docs
Requires-Dist: furo; extra == 'docs'
Requires-Dist: sphinx>=4.0.0; extra == 'docs'
Requires-Dist: sphinxcontrib-programoutput; extra == 'docs'
Provides-Extra: ldap
Requires-Dist: python-ldap<4.0,>=3.4; extra == 'ldap'
Provides-Extra: openstack
Requires-Dist: osc-lib~=2.2.0; extra == 'openstack'
Provides-Extra: test
Requires-Dist: pytest-click>=1.1.0; extra == 'test'
Requires-Dist: pytest-cov>=5.0.0; extra == 'test'
Requires-Dist: pytest-datafiles>=3.0.0; extra == 'test'
Requires-Dist: pytest-mock>=3.14.0; extra == 'test'
Requires-Dist: pytest-responses>=0.5.1; extra == 'test'
Requires-Dist: pytest>=8.3.0; extra == 'test'
